{
  "_type": "https://in-toto.io/Statement/v1",
  "predicateType": "https://slsa.dev/provenance/v1",
  "subject": [
    {
      "name": "bundle/.mcp.json",
      "digest": {
        "sha256": "e16897732dbd20ba7f47e5c0513b146a8d847454c8c13aa9e0a6031e5a498fa4"
      }
    }
  ],
  "predicate": {
    "buildType": "https://omg.security/offline-attestation/v1",
    "metadata": {
      "signer": {
        "keyid": "1f5fe64ec2f8c901",
        "algorithm": "ed25519-minisign",
        "mode": "local-offline"
      },
      "timestamp": "2026-03-14T04:21:32.320194+00:00"
    }
  },
  "signer": {
    "keyid": "1f5fe64ec2f8c901",
    "algorithm": "ed25519-minisign",
    "mode": "local-offline"
  },
  "issued_at": "2026-03-14T04:21:32.320194+00:00",
  "signature": {
    "alg": "ed25519-minisign",
    "keyid": "681a2ca59eb04910",
    "value": "untrusted comment: signature from omg local signing key\nh/6Zeq7m8iW3TDpJvsz2DG3iT2dR9QvzXWMoV4+1ArXDtnRMWqPtxxUr3nEqiEzj3p58yoWl/9odm/DPVEZIBg==\ntrusted comment: type=omg-slsa-v1 keyid=681a2ca59eb04910 issued_at=2026-03-14T04:21:32.320300+00:00 artifact=bundle/.mcp.json sha256=e16897732dbd20ba7f47e5c0513b146a8d847454c8c13aa9e0a6031e5a498fa4\n4b7xKrXWiiHgfTVcP/VrUrN4JxTsccaxNQtQnkgzW7RDW+VolyUTnTdprcA4kshEjWflwpe0u1L9LcvQxhYBDg==",
    "trusted_comment": "type=omg-slsa-v1 keyid=681a2ca59eb04910 issued_at=2026-03-14T04:21:32.320300+00:00 artifact=bundle/.mcp.json sha256=e16897732dbd20ba7f47e5c0513b146a8d847454c8c13aa9e0a6031e5a498fa4"
  }
}
