{
  "_type": "https://in-toto.io/Statement/v1",
  "predicateType": "https://slsa.dev/provenance/v1",
  "subject": [
    {
      "name": "bundle/.mcp.json",
      "digest": {
        "sha256": "e16897732dbd20ba7f47e5c0513b146a8d847454c8c13aa9e0a6031e5a498fa4"
      }
    }
  ],
  "predicate": {
    "buildType": "https://omg.security/offline-attestation/v1",
    "metadata": {
      "signer": {
        "keyid": "1f5fe64ec2f8c901",
        "algorithm": "ed25519-minisign",
        "mode": "local-offline"
      },
      "timestamp": "2026-03-13T00:09:43.780921+00:00"
    }
  },
  "signer": {
    "keyid": "1f5fe64ec2f8c901",
    "algorithm": "ed25519-minisign",
    "mode": "local-offline"
  },
  "issued_at": "2026-03-13T00:09:43.780921+00:00",
  "signature": {
    "alg": "ed25519-minisign",
    "keyid": "1082c7a6ddb473a6",
    "value": "untrusted comment: signature from omg local signing key\nPIMSmxyfI51Y4253zMUc6UY69BrFxtMEJ4AT5Wl9KOmcxMuZagDAVDG3q1+B96zqs7r3UToQr02Qfvmms/SNBA==\ntrusted comment: type=omg-slsa-v1 keyid=1082c7a6ddb473a6 issued_at=2026-03-13T00:09:43.781031+00:00 artifact=bundle/.mcp.json sha256=e16897732dbd20ba7f47e5c0513b146a8d847454c8c13aa9e0a6031e5a498fa4\n2LCrORd/P3m1Hoik/NkQ7Vp1DYtmy0DD5z5MC5KGWKl+jCo+f0TrzQc46CaFCjo8DdCV1b9qQYv7MufVZdjIBg==",
    "trusted_comment": "type=omg-slsa-v1 keyid=1082c7a6ddb473a6 issued_at=2026-03-13T00:09:43.781031+00:00 artifact=bundle/.mcp.json sha256=e16897732dbd20ba7f47e5c0513b146a8d847454c8c13aa9e0a6031e5a498fa4"
  }
}
