{
  "_type": "https://in-toto.io/Statement/v1",
  "predicateType": "https://slsa.dev/provenance/v1",
  "subject": [
    {
      "name": "bundle/.kimi/mcp.json",
      "digest": {
        "sha256": "39e1aa3014e4f022e31f725adbe84b2d8c05c5d377e9be21470422dff1e84757"
      }
    }
  ],
  "predicate": {
    "buildType": "https://omg.security/offline-attestation/v1",
    "metadata": {
      "signer": {
        "keyid": "1f5fe64ec2f8c901",
        "algorithm": "ed25519-minisign",
        "mode": "local-offline"
      },
      "timestamp": "2026-03-16T19:27:39.065963+00:00"
    }
  },
  "signer": {
    "keyid": "1f5fe64ec2f8c901",
    "algorithm": "ed25519-minisign",
    "mode": "local-offline"
  },
  "issued_at": "2026-03-16T19:27:39.065963+00:00",
  "signature": {
    "alg": "ed25519-minisign",
    "keyid": "4763ea76b6ecf237",
    "value": "untrusted comment: signature from omg local signing key\nAyGunpWGO9wLFN8KInH3IHeN0dJypXoQeG2X99RxmNPZdMI+Ns0/dEDicnAgTyH4J2WBgtAo03Az73I90iZ2AQ==\ntrusted comment: type=omg-slsa-v1 keyid=4763ea76b6ecf237 issued_at=2026-03-16T19:27:39.066071+00:00 artifact=bundle/.kimi/mcp.json sha256=39e1aa3014e4f022e31f725adbe84b2d8c05c5d377e9be21470422dff1e84757\ndmm+U937jW74Fo9+wQW6cDSIyCiYUp8sB6HWMPz56Tq10vZgIKNaPphAiuZf0QS4I9CtfWMyQWpHxM4hTYm0Aw==",
    "trusted_comment": "type=omg-slsa-v1 keyid=4763ea76b6ecf237 issued_at=2026-03-16T19:27:39.066071+00:00 artifact=bundle/.kimi/mcp.json sha256=39e1aa3014e4f022e31f725adbe84b2d8c05c5d377e9be21470422dff1e84757"
  }
}
